nonebot_plugin_setu2/__init__.py
nonebot_plugin_setu2/config.py
nonebot_plugin_setu2/get_data.py
nonebot_plugin_setu2/json_manager.py
nonebot_plugin_setu2/setu_message.py
nonebot_plugin_setu2-0.1.1.dist-info/LICENSE
nonebot_plugin_setu2-0.1.1.dist-info/WHEEL
nonebot_plugin_setu2-0.1.1.dist-info/METADATA
nonebot_plugin_setu2-0.1.1.dist-info/RECORD
