Metadata-Version: 2.1
Name: nonebot-plugin-setu2
Version: 0.1.1
Summary: 
License: MIT
Author: alphaAE
Author-email: a1226123914@gmail.com
Requires-Python: >=3.9,<4.0
Classifier: License :: OSI Approved :: MIT License
Classifier: Programming Language :: Python :: 3
Classifier: Programming Language :: Python :: 3.10
Classifier: Programming Language :: Python :: 3.9
Requires-Dist: httpx (>=0.22.0,<0.23.0)
Requires-Dist: httpx-socks (>=0.7.3,<0.8.0)
Requires-Dist: nonebot-adapter-onebot (>=2.0.0-beta.1,<3.0.0)
Requires-Dist: nonebot2 (>=2.0.0-beta.1,<3.0.0)
